eapi-sdk/__init__.py
eapi-sdk/client.py
eapi-sdk/exceptions.py
eapi-sdk/main.py
eapi-sdk/models.py
eapi-sdk/utils.py
eapisdk/__init__.py
eapisdk/client.py
eapisdk/exceptions.py
eapisdk/main.py
eapisdk/models.py
eapisdk/utils.py
EAPI_SDK-1.0.3.dist-info/METADATA
EAPI_SDK-1.0.3.dist-info/WHEEL
EAPI_SDK-1.0.3.dist-info/licence.txt
EAPI_SDK-1.0.3.dist-info/top_level.txt
EAPI_SDK-1.0.3.dist-info/RECORD
